visuallayer/__init__.py
visuallayer/sentry.py
visuallayer/datasets/__init__.py
visuallayer/datasets/clean_torchvision_food101.py
visuallayer/datasets/clean_torchvision_imagenet.py
visuallayer/datasets/clean_torchvision_kitti.py
visuallayer/datasets/clean_torchvision_oxford_iiit_pet.py
visuallayer/datasets/dataset.py
visuallayer/datasets/image_folder.py
visuallayer/datasets/vl_cocodetection.py
visuallayer/datasets/vl_parse_exclude_csv.py
visuallayer/datasets/zoo/__init__.py
visuallayer/datasets/zoo/utils.py
visuallayer/datasets/zoo/vl_food101.py
visuallayer/datasets/zoo/vl_imagenet.py
visuallayer/datasets/zoo/vl_kitti.py
visuallayer/datasets/zoo/vl_oxford_iiit.py
visuallayer-0.0.15.dist-info/LICENSE
visuallayer-0.0.15.dist-info/METADATA
visuallayer-0.0.15.dist-info/WHEEL
visuallayer-0.0.15.dist-info/top_level.txt
visuallayer-0.0.15.dist-info/RECORD
